prescience/__init__.py
prescience-0.0.0a2.dist-info/LICENSE
prescience-0.0.0a2.dist-info/METADATA
prescience-0.0.0a2.dist-info/WHEEL
prescience-0.0.0a2.dist-info/top_level.txt
prescience-0.0.0a2.dist-info/RECORD
