Metadata-Version: 2.1
Name: prescience
Version: 0.0.0a2
Summary: Fully Bayesian Forecasting
Author-email: Thomas Gessey-Jones <thomasgesseyjones@gmail.com>
Maintainer-email: Thomas Gessey-Jones <thomasgesseyjones@gmail.com>
License: MIT License
Project-URL: Homepage, https://github.com/ThomasGesseyJones/prescience
Project-URL: Bug Tracker, https://github.com/ThomasGesseyJones/prescience/issues
Classifier: Programming Language :: Python :: 3
Classifier: Operating System :: OS Independent
Classifier: Development Status :: 2 - Pre-Alpha
Classifier: Natural Language :: English
Classifier: License :: OSI Approved :: MIT License
Classifier: Topic :: Scientific/Engineering
Requires-Python: >=3.8
License-File: LICENSE
